{"v":"5.7.3","fr":60,"ip":0,"op":241,"w":750,"h":500,"nm":"Error_01","ddd":0,"assets":[],"layers":[{"ddd":0,"ind":1,"ty":4,"nm":"ALpha 2","td":1,"sr":1,"ks":{"o":{"a":0,"k":100,"ix":11},"r":{"a":0,"k":0,"ix":10},"p":{"a":0,"k":[375,250,0],"ix":2},"a":{"a":0,"k":[0,0,0],"ix":1},"s":{"a":0,"k":[100,110.46,100],"ix":6}},"ao":0,"shapes":[{"ty":"gr","it":[{"ty":"rc","d":1,"s":{"a":0,"k":[234,106],"ix":2},"p":{"a":0,"k":[0,0],"ix":3},"r":{"a":0,"k":0,"ix":4},"nm":"Rectangle Path 1","mn":"ADBE Vector Shape - Rect","hd":false},{"ty":"st","c":{"a":0,"k":[0.527842981675,0.117987995522,0.276641995299,1],"ix":3},"o":{"a":0,"k":100,"ix":4},"w":{"a":0,"k":0,"ix":5},"lc":1,"lj":1,"ml":4,"bm":0,"nm":"Stroke 1","mn":"ADBE Vector Graphic - Stroke","hd":false},{"ty":"fl","c":{"a":0,"k":[0.117646998985,0.60784295774,0.050980003207,1],"ix":4},"o":{"a":0,"k":100,"ix":5},"r":1,"bm":0,"nm":"Fill 1","mn":"ADBE Vector Graphic - Fill","hd":false},{"ty":"tr","p":{"a":0,"k":[15,186],"ix":2},"a":{"a":0,"k":[0,0],"ix":1},"s":{"a":0,"k":[126.446,100],"ix":3},"r":{"a":0,"k":0,"ix":6},"o":{"a":0,"k":100,"ix":7},"sk":{"a":0,"k":0,"ix":4},"sa":{"a":0,"k":0,"ix":5},"nm":"Transform"}],"nm":"Rectangle 1","np":3,"cix":2,"bm":0,"ix":1,"mn":"ADBE Vector Group","hd":false}],"ip":0,"op":10812,"st":0,"bm":0},{"ddd":0,"ind":2,"ty":4,"nm":"Error Board Outlines","parent":6,"tt":2,"sr":1,"ks":{"o":{"a":1,"k":[{"i":{"x":[0.833],"y":[0.833]},"o":{"x":[0.167],"y":[0.167]},"t":84,"s":[0]},{"t":98,"s":[100]}],"ix":11},"r":{"a":0,"k":-0.4,"ix":10},"p":{"a":0,"k":[12.951,9.637,0],"ix":2},"a":{"a":0,"k":[135.215,162.02,0],"ix":1},"s":{"a":1,"k":[{"i":{"x":[0.16,0.16,0.16],"y":[1,1,1]},"o":{"x":[0.84,0.84,0.84],"y":[0,0,0]},"t":40.365,"s":[0,0,100]},{"t":150.365234375,"s":[100,100,100]}],"ix":6}},"ao":0,"shapes":[{"ty":"gr","it":[{"ind":0,"ty":"sh","ix":1,"ks":{"a":0,"k":{"i":[[2.48,0],[0.302,-0.025],[0,0],[1.815,-2.149],[-0.236,-2.803],[0,0],[-2.149,-1.814],[-2.804,0.234],[0,0],[-1.815,2.148],[0.236,2.803],[0,0],[2.149,1.815]],"o":[[-0.3,0],[0,0],[-2.803,0.236],[-1.815,2.149],[0,0],[0.237,2.803],[2.149,1.815],[0,0],[2.802,-0.236],[1.814,-2.15],[0,0],[-0.237,-2.803],[-1.918,-1.618]],"v":[[110.49,-77.082],[109.587,-77.044],[-121.235,-57.572],[-128.395,-53.873],[-130.843,-46.195],[-121.239,67.654],[-117.539,74.814],[-109.861,77.262],[120.961,57.79],[128.121,54.092],[130.568,46.413],[120.964,-67.436],[117.265,-74.597]],"c":true},"ix":2},"nm":"Path 1","mn":"ADBE Vector Shape - Group","hd":false},{"ind":1,"ty":"sh","ix":2,"ks":{"a":0,"k":{"i":[[0.326,0],[2.091,1.766],[0.258,3.056],[0,0],[-1.979,2.343],[-3.056,0.257],[0,0],[-2.344,-1.979],[-0.258,-3.056],[0,0],[6.308,-0.532],[0,0],[0,0],[0,0]],"o":[[-2.705,0],[-2.343,-1.978],[0,0],[-0.258,-3.056],[1.978,-2.344],[0,0],[3.046,-0.26],[2.342,1.979],[0,0],[0.532,6.309],[0,0],[0,0],[0,0],[-0.329,0.027]],"v":[[-110.765,78.252],[-118.154,75.542],[-122.187,67.734],[-131.791,-46.115],[-129.122,-54.487],[-121.315,-58.52],[109.507,-77.992],[117.88,-75.324],[121.913,-67.517],[131.517,46.333],[121.041,58.739],[121.001,58.265],[121.041,58.739],[-109.781,78.211]],"c":true},"ix":2},"nm":"Path 2","mn":"ADBE Vector Shape - Group","hd":false},{"ty":"mm","mm":1,"nm":"Merge Paths 1","mn":"ADBE Vector Filter - Merge","hd":false},{"ty":"mm","mm":4,"nm":"Merge Paths 2","mn":"ADBE Vector Filter - Merge","hd":false},{"ty":"fl","c":{"a":0,"k":[0,0,0,1],"ix":4},"o":{"a":0,"k":100,"ix":5},"r":2,"bm":0,"nm":"Fill 1","mn":"ADBE Vector Graphic - Fill","hd":false},{"ty":"tr","p":{"a":0,"k":[139.232,84.302],"ix":2},"a":{"a":0,"k":[0,0],"ix":1},"s":{"a":0,"k":[100,100],"ix":3},"r":{"a":0,"k":0,"ix":6},"o":{"a":0,"k":100,"ix":7},"sk":{"a":0,"k":0,"ix":4},"sa":{"a":0,"k":0,"ix":5},"nm":"Transform"}],"nm":"Group 1","np":5,"cix":2,"bm":0,"ix":1,"mn":"ADBE Vector Group","hd":false},{"ty":"gr","it":[{"ind":0,"ty":"sh","ix":1,"ks":{"a":0,"k":{"i":[[0,0],[0,0],[-0.184,0.197],[0.033,0.384],[0.222,0.18],[0.385,-0.033],[0,0]],"o":[[0,0],[0.397,-0.034],[0.183,-0.198],[-0.029,-0.348],[-0.221,-0.182],[0,0],[0,0]],"v":[[-1.528,-0.938],[0.111,-1.076],[0.982,-1.421],[1.208,-2.293],[0.832,-3.087],[-0.078,-3.31],[-1.716,-3.172]],"c":true},"ix":2},"nm":"Path 1","mn":"ADBE Vector Shape - Group","hd":false},{"ind":1,"ty":"sh","ix":2,"ks":{"a":0,"k":{"i":[[0,0],[0,0],[0,0],[0,0],[0,0],[0,0],[0,0],[-0.79,-0.315],[-0.433,-0.621],[-0.07,-0.819],[0.433,-0.724],[0.893,-0.376],[0,0]],"o":[[0,0],[0,0],[0,0],[0,0],[0,0],[0,0],[1.069,-0.09],[0.789,0.315],[0.434,0.619],[0.074,0.881],[-0.432,0.725],[0,0],[0,0]],"v":[[1.599,6.338],[-1.277,1.818],[-1.296,1.819],[-0.896,6.548],[-5.031,6.897],[-6.143,-6.289],[0.002,-6.807],[2.788,-6.469],[4.622,-5.067],[5.377,-2.908],[4.839,-0.5],[2.85,1.15],[6.143,5.955]],"c":true},"ix":2},"nm":"Path 2","mn":"ADBE Vector Shape - Group","hd":false},{"ty":"mm","mm":1,"nm":"Merge Paths 1","mn":"ADBE Vector Filter - Merge","hd":false},{"ty":"mm","mm":4,"nm":"Merge Paths 2","mn":"ADBE Vector Filter - Merge","hd":false},{"ty":"fl","c":{"a":0,"k":[0.238999998803,0.149000010771,0,1],"ix":4},"o":{"a":0,"k":100,"ix":5},"r":1,"bm":0,"nm":"Fill 1","mn":"ADBE Vector Graphic - Fill","hd":false},{"ty":"tr","p":{"a":0,"k":[182.024,37.854],"ix":2},"a":{"a":0,"k":[0,0],"ix":1},"s":{"a":0,"k":[100,100],"ix":3},"r":{"a":0,"k":0,"ix":6},"o":{"a":0,"k":100,"ix":7},"sk":{"a":0,"k":0,"ix":4},"sa":{"a":0,"k":0,"ix":5},"nm":"Transform"}],"nm":"Group 2","np":5,"cix":2,"bm":0,"ix":2,"mn":"ADBE Vector Group","hd":false},{"ty":"gr","it":[{"ind":0,"ty":"sh","ix":1,"ks":{"a":0,"k":{"i":[[-0.403,0.565],[0.075,0.893],[0.491,0.49],[0.818,-0.069],[0.403,-0.565],[-0.076,-0.906],[-0.493,-0.489],[-0.832,0.07]],"o":[[0.402,-0.565],[-0.076,-0.907],[-0.492,-0.489],[-0.832,0.07],[-0.403,0.566],[0.076,0.894],[0.49,0.49],[0.819,-0.069]],"v":[[2.098,1.963],[2.588,-0.226],[1.736,-2.321],[-0.23,-2.951],[-2.081,-1.998],[-2.571,0.209],[-1.719,2.286],[0.265,2.915]],"c":true},"ix":2},"nm":"Path 1","mn":"ADBE Vector Shape - Group","hd":false},{"ind":1,"ty":"sh","ix":2,"ks":{"a":0,"k":{"i":[[1.086,0.497],[0.695,0.979],[0.108,1.292],[-0.521,1.081],[-0.988,0.666],[-1.243,0.104],[-1.079,-0.491],[-0.689,-0.98],[-0.11,-1.291],[0.516,-1.08],[0.988,-0.671],[1.23,-0.104]],"o":[[-1.086,-0.495],[-0.695,-0.979],[-0.108,-1.291],[0.522,-1.082],[0.987,-0.664],[1.241,-0.105],[1.079,0.491],[0.69,0.979],[0.109,1.292],[-0.515,1.082],[-0.988,0.67],[-1.241,0.104]],"v":[[-2.902,6.183],[-5.574,3.971],[-6.779,0.564],[-6.161,-2.994],[-3.896,-5.615],[-0.551,-6.769],[2.929,-6.191],[5.58,-3.985],[6.779,-0.58],[6.169,2.98],[3.915,5.609],[0.589,6.77]],"c":true},"ix":2},"nm":"Path 2","mn":"ADBE Vector Shape - Group","hd":false},{"ty":"mm","mm":1,"nm":"Merge Paths 1","mn":"ADBE Vector Filter - Merge","hd":false},{"ty":"mm","mm":4,"nm":"Merge Paths 2","mn":"ADBE Vector Filter - Merge","hd":false},{"ty":"fl","c":{"a":0,"k":[0.238999998803,0.149000010771,0,1],"ix":4},"o":{"a":0,"k":100,"ix":5},"r":1,"bm":0,"nm":"Fill 1","mn":"ADBE Vector Graphic - Fill","hd":false},{"ty":"tr","p":{"a":0,"k":[159.224,39.561],"ix":2},"a":{"a":0,"k":[0,0],"ix":1},"s":{"a":0,"k":[100,100],"ix":3},"r":{"a":0,"k":0,"ix":6},"o":{"a":0,"k":100,"ix":7},"sk":{"a":0,"k":0,"ix":4},"sa":{"a":0,"k":0,"ix":5},"nm":"Transform"}],"nm":"Group 3","np":5,"cix":2,"bm":0,"ix":3,"mn":"ADBE Vector Group","hd":false},{"ty":"gr","it":[{"ind":0,"ty":"sh","ix":1,"ks":{"a":0,"k":{"i":[[0,0],[0,0],[-0.183,0.197],[0.033,0.384],[0.222,0.18],[0.385,-0.033],[0,0]],"o":[[0,0],[0.397,-0.034],[0.183,-0.198],[-0.029,-0.348],[-0.221,-0.182],[0,0],[0,0]],"v":[[-1.528,-0.938],[0.111,-1.076],[0.982,-1.421],[1.208,-2.293],[0.832,-3.087],[-0.078,-3.31],[-1.716,-3.172]],"c":true},"ix":2},"nm":"Path 1","mn":"ADBE Vector Shape - Group","hd":false},{"ind":1,"ty":"sh","ix":2,"ks":{"a":0,"k":{"i":[[0,0],[0,0],[0,0],[0,0],[0,0],[0,0],[0,0],[-0.789,-0.315],[-0.434,-0.621],[-0.07,-0.819],[0.433,-0.724],[0.893,-0.376],[0,0]],"o":[[0,0],[0,0],[0,0],[0,0],[0,0],[0,0],[1.069,-0.09],[0.789,0.315],[0.433,0.619],[0.074,0.881],[-0.433,0.725],[0,0],[0,0]],"v":[[1.599,6.338],[-1.277,1.818],[-1.296,1.819],[-0.896,6.548],[-5.031,6.897],[-6.143,-6.289],[0.002,-6.807],[2.788,-6.469],[4.623,-5.067],[5.377,-2.908],[4.839,-0.5],[2.85,1.15],[6.143,5.955]],"c":true},"ix":2},"nm":"Path 2","mn":"ADBE Vector Shape - Group","hd":false},{"ty":"mm","mm":1,"nm":"Merge Paths 1","mn":"ADBE Vector Filter - Merge","hd":false},{"ty":"mm","mm":4,"nm":"Merge Paths 2","mn":"ADBE Vector Filter - Merge","hd":false},{"ty":"fl","c":{"a":0,"k":[0.238999998803,0.149000010771,0,1],"ix":4},"o":{"a":0,"k":100,"ix":5},"r":1,"bm":0,"nm":"Fill 1","mn":"ADBE Vector Graphic - Fill","hd":false},{"ty":"tr","p":{"a":0,"k":[136.991,41.652],"ix":2},"a":{"a":0,"k":[0,0],"ix":1},"s":{"a":0,"k":[100,100],"ix":3},"r":{"a":0,"k":0,"ix":6},"o":{"a":0,"k":100,"ix":7},"sk":{"a":0,"k":0,"ix":4},"sa":{"a":0,"k":0,"ix":5},"nm":"Transform"}],"nm":"Group 4","np":5,"cix":2,"bm":0,"ix":4,"mn":"ADBE Vector Group","hd":false},{"ty":"gr","it":[{"ind":0,"ty":"sh","ix":1,"ks":{"a":0,"k":{"i":[[0,0],[0,0],[-0.184,0.197],[0.033,0.384],[0.222,0.181],[0.385,-0.033],[0,0]],"o":[[0,0],[0.397,-0.034],[0.183,-0.198],[-0.029,-0.348],[-0.221,-0.182],[0,0],[0,0]],"v":[[-1.528,-0.938],[0.111,-1.076],[0.982,-1.421],[1.208,-2.293],[0.832,-3.087],[-0.078,-3.31],[-1.716,-3.172]],"c":true},"ix":2},"nm":"Path 1","mn":"ADBE Vector Shape - Group","hd":false},{"ind":1,"ty":"sh","ix":2,"ks":{"a":0,"k":{"i":[[0,0],[0,0],[0,0],[0,0],[0,0],[0,0],[0,0],[-0.79,-0.315],[-0.433,-0.62],[-0.069,-0.819],[0.433,-0.724],[0.894,-0.375],[0,0]],"o":[[0,0],[0,0],[0,0],[0,0],[0,0],[0,0],[1.068,-0.091],[0.789,0.315],[0.434,0.619],[0.075,0.881],[-0.433,0.725],[0,0],[0,0]],"v":[[1.599,6.338],[-1.277,1.818],[-1.296,1.819],[-0.897,6.548],[-5.031,6.897],[-6.143,-6.289],[0.002,-6.806],[2.788,-6.469],[4.622,-5.067],[5.376,-2.908],[4.839,-0.5],[2.849,1.15],[6.143,5.955]],"c":true},"ix":2},"nm":"Path 2","mn":"ADBE Vector Shape - Group","hd":false},{"ty":"mm","mm":1,"nm":"Merge Paths 1","mn":"ADBE Vector Filter - Merge","hd":false},{"ty":"mm","mm":4,"nm":"Merge Paths 2","mn":"ADBE Vector Filter - Merge","hd":false},{"ty":"fl","c":{"a":0,"k":[0.238999998803,0.149000010771,0,1],"ix":4},"o":{"a":0,"k":100,"ix":5},"r":1,"bm":0,"nm":"Fill 1","mn":"ADBE Vector Graphic - Fill","hd":false},{"ty":"tr","p":{"a":0,"k":[115.574,43.459],"ix":2},"a":{"a":0,"k":[0,0],"ix":1},"s":{"a":0,"k":[100,100],"ix":3},"r":{"a":0,"k":0,"ix":6},"o":{"a":0,"k":100,"ix":7},"sk":{"a":0,"k":0,"ix":4},"sa":{"a":0,"k":0,"ix":5},"nm":"Transform"}],"nm":"Group 5","np":6,"cix":2,"bm":0,"ix":5,"mn":"ADBE Vector Group","hd":false},{"ty":"gr","it":[{"ind":0,"ty":"sh","ix":1,"ks":{"a":0,"k":{"i":[[0,0],[0,0],[0,0],[0,0],[0,0],[0,0],[0,0],[0,0],[0,0],[0,0],[0,0],[0,0]],"o":[[0,0],[0,0],[0,0],[0,0],[0,0],[0,0],[0,0],[0,0],[0,0],[0,0],[0,0],[0,0]],"v":[[-0.538,-3.275],[-0.401,-1.654],[3.695,-2],[3.957,1.111],[-0.139,1.456],[0.018,3.318],[4.673,2.925],[4.952,6.222],[-3.84,6.963],[-4.952,-6.222],[3.84,-6.963],[4.117,-3.668]],"c":true},"ix":2},"nm":"Path 1","mn":"ADBE Vector Shape - Group","hd":false},{"ty":"mm","mm":4,"nm":"Merge Paths 1","mn":"ADBE Vector Filter - Merge","hd":false},{"ty":"fl","c":{"a":0,"k":[0.238999998803,0.149000010771,0,1],"ix":4},"o":{"a":0,"k":100,"ix":5},"r":1,"bm":0,"nm":"Fill 1","mn":"ADBE Vector Graphic - Fill","hd":false},{"ty":"tr","p":{"a":0,"k":[95.088,45.021],"ix":2},"a":{"a":0,"k":[0,0],"ix":1},"s":{"a":0,"k":[100,100],"ix":3},"r":{"a":0,"k":0,"ix":6},"o":{"a":0,"k":100,"ix":7},"sk":{"a":0,"k":0,"ix":4},"sa":{"a":0,"k":0,"ix":5},"nm":"Transform"}],"nm":"Group 6","np":4,"cix":2,"bm":0,"ix":6,"mn":"ADBE Vector Group","hd":false},{"ty":"gr","it":[{"ind":0,"ty":"sh","ix":1,"ks":{"a":0,"k":{"i":[[0,0],[0,0],[0,0]],"o":[[0,0],[0,0],[0,0]],"v":[[0.415,-9.811],[-8.902,7.43],[1.794,6.528]],"c":true},"ix":2},"nm":"Path 1","mn":"ADBE Vector Shape - Group","hd":false},{"ind":1,"ty":"sh","ix":2,"ks":{"a":0,"k":{"i":[[0,0],[0,0],[0,0],[0,0],[0,0],[0,0],[0,0],[0,0],[0,0],[0,0],[0,0]],"o":[[0,0],[0,0],[0,0],[0,0],[0,0],[0,0],[0,0],[0,0],[0,0],[0,0],[0,0]],"v":[[-29.383,28.308],[-30.928,9.988],[-4.967,-34.59],[18.701,-36.586],[22.193,4.807],[29.324,4.206],[30.928,23.22],[23.798,23.822],[24.716,34.715],[2.533,36.586],[1.614,25.693]],"c":true},"ix":2},"nm":"Path 2","mn":"ADBE Vector Shape - Group","hd":false},{"ty":"mm","mm":1,"nm":"Merge Paths 1","mn":"ADBE Vector Filter - Merge","hd":false},{"ty":"mm","mm":4,"nm":"Merge Paths 2","mn":"ADBE Vector Filter - Merge","hd":false},{"ty":"fl","c":{"a":0,"k":[0.238999998803,0.149000010771,0,1],"ix":4},"o":{"a":0,"k":100,"ix":5},"r":1,"bm":0,"nm":"Fill 1","mn":"ADBE Vector Graphic - Fill","hd":false},{"ty":"tr","p":{"a":0,"k":[208.211,88.02],"ix":2},"a":{"a":0,"k":[0,0],"ix":1},"s":{"a":0,"k":[100,100],"ix":3},"r":{"a":0,"k":0,"ix":6},"o":{"a":0,"k":100,"ix":7},"sk":{"a":0,"k":0,"ix":4},"sa":{"a":0,"k":0,"ix":5},"nm":"Transform"}],"nm":"Group 7","np":6,"cix":2,"bm":0,"ix":7,"mn":"ADBE Vector Group","hd":false},{"ty":"gr","it":[{"ind":0,"ty":"sh","ix":1,"ks":{"a":0,"k":{"i":[[1.281,2.585],[3.233,-0.272],[0.83,-2.763],[-0.446,-5.282],[-1.282,-2.584],[-3.302,0.279],[-0.832,2.764],[0.451,5.347]],"o":[[-1.282,-2.584],[-3.303,0.28],[-0.831,2.762],[0.451,5.348],[1.281,2.586],[3.233,-0.273],[0.83,-2.762],[-0.446,-5.283]],"v":[[5.43,-12.529],[-1.344,-15.997],[-7.543,-11.434],[-8.12,0.633],[-5.521,12.531],[1.354,15.991],[7.452,11.436],[8.022,-0.728]],"c":true},"ix":2},"nm":"Path 1","mn":"ADBE Vector Shape - Group","hd":false},{"ind":1,"ty":"sh","ix":2,"ks":{"a":0,"k":{"i":[[-4.301,6.944],[-10.101,0.853],[-5.441,-6.156],[-0.958,-11.356],[4.33,-6.98],[10.034,-0.845],[5.407,6.162],[0.964,11.422]],"o":[[4.301,-6.946],[10.034,-0.845],[5.439,6.157],[0.964,11.422],[-4.332,6.983],[-10.101,0.852],[-5.406,-6.159],[-0.964,-11.42]],"v":[[-24.703,-25.096],[-3.099,-36.793],[20.113,-28.827],[29.709,-2.558],[24.658,25.045],[3.108,36.786],[-20.154,28.825],[-29.709,2.454]],"c":true},"ix":2},"nm":"Path 2","mn":"ADBE Vector Shape - Group","hd":false},{"ty":"mm","mm":1,"nm":"Merge Paths 1","mn":"ADBE Vector Filter - Merge","hd":false},{"ty":"mm","mm":4,"nm":"Merge Paths 2","mn":"ADBE Vector Filter - Merge","hd":false},{"ty":"fl","c":{"a":0,"k":[0.238999998803,0.149000010771,0,1],"ix":4},"o":{"a":0,"k":100,"ix":5},"r":1,"bm":0,"nm":"Fill 1","mn":"ADBE Vector Graphic - Fill","hd":false},{"ty":"tr","p":{"a":0,"k":[138.778,93.229],"ix":2},"a":{"a":0,"k":[0,0],"ix":1},"s":{"a":0,"k":[100,100],"ix":3},"r":{"a":0,"k":0,"ix":6},"o":{"a":0,"k":100,"ix":7},"sk":{"a":0,"k":0,"ix":4},"sa":{"a":0,"k":0,"ix":5},"nm":"Transform"}],"nm":"Group 8","np":6,"cix":2,"bm":0,"ix":8,"mn":"ADBE Vector Group","hd":false},{"ty":"gr","it":[{"ind":0,"ty":"sh","ix":1,"ks":{"a":0,"k":{"i":[[0,0],[0,0],[0,0]],"o":[[0,0],[0,0],[0,0]],"v":[[0.415,-9.811],[-8.903,7.43],[1.792,6.529]],"c":true},"ix":2},"nm":"Path 1","mn":"ADBE Vector Shape - Group","hd":false},{"ind":1,"ty":"sh","ix":2,"ks":{"a":0,"k":{"i":[[0,0],[0,0],[0,0],[0,0],[0,0],[0,0],[0,0],[0,0],[0,0],[0,0],[0,0]],"o":[[0,0],[0,0],[0,0],[0,0],[0,0],[0,0],[0,0],[0,0],[0,0],[0,0],[0,0]],"v":[[-29.383,28.308],[-30.928,9.988],[-4.968,-34.589],[18.701,-36.586],[22.193,4.807],[29.324,4.206],[30.928,23.22],[23.798,23.822],[24.716,34.715],[2.533,36.586],[1.614,25.693]],"c":true},"ix":2},"nm":"Path 2","mn":"ADBE Vector Shape - Group","hd":false},{"ty":"mm","mm":1,"nm":"Merge Paths 1","mn":"ADBE Vector Filter - Merge","hd":false},{"ty":"fl","c":{"a":0,"k":[0.238999998803,0.149000010771,0,1],"ix":4},"o":{"a":0,"k":100,"ix":5},"r":1,"bm":0,"nm":"Fill 1","mn":"ADBE Vector Graphic - Fill","hd":false},{"ty":"tr","p":{"a":0,"k":[72.938,99.431],"ix":2},"a":{"a":0,"k":[0,0],"ix":1},"s":{"a":0,"k":[100,100],"ix":3},"r":{"a":0,"k":0,"ix":6},"o":{"a":0,"k":100,"ix":7},"sk":{"a":0,"k":0,"ix":4},"sa":{"a":0,"k":0,"ix":5},"nm":"Transform"}],"nm":"Group 9","np":4,"cix":2,"bm":0,"ix":9,"mn":"ADBE Vector Group","hd":false}],"ip":0,"op":10812,"st":0,"bm":0},{"ddd":0,"ind":3,"ty":4,"nm":"ALpha 4","td":1,"sr":1,"ks":{"o":{"a":0,"k":100,"ix":11},"r":{"a":0,"k":0,"ix":10},"p":{"a":0,"k":[375,250,0],"ix":2},"a":{"a":0,"k":[0,0,0],"ix":1},"s":{"a":0,"k":[100,110.46,100],"ix":6}},"ao":0,"shapes":[{"ty":"gr","it":[{"ty":"rc","d":1,"s":{"a":0,"k":[234,106],"ix":2},"p":{"a":0,"k":[0,0],"ix":3},"r":{"a":0,"k":0,"ix":4},"nm":"Rectangle Path 1","mn":"ADBE Vector Shape - Rect","hd":false},{"ty":"st","c":{"a":0,"k":[0.527842981675,0.117987995522,0.276641995299,1],"ix":3},"o":{"a":0,"k":100,"ix":4},"w":{"a":0,"k":0,"ix":5},"lc":1,"lj":1,"ml":4,"bm":0,"nm":"Stroke 1","mn":"ADBE Vector Graphic - Stroke","hd":false},{"ty":"fl","c":{"a":0,"k":[0.117646998985,0.60784295774,0.050980003207,1],"ix":4},"o":{"a":0,"k":100,"ix":5},"r":1,"bm":0,"nm":"Fill 1","mn":"ADBE Vector Graphic - Fill","hd":false},{"ty":"tr","p":{"a":0,"k":[15,186],"ix":2},"a":{"a":0,"k":[0,0],"ix":1},"s":{"a":0,"k":[126.446,100],"ix":3},"r":{"a":0,"k":0,"ix":6},"o":{"a":0,"k":100,"ix":7},"sk":{"a":0,"k":0,"ix":4},"sa":{"a":0,"k":0,"ix":5},"nm":"Transform"}],"nm":"Rectangle 1","np":3,"cix":2,"bm":0,"ix":1,"mn":"ADBE Vector Group","hd":false}],"ip":0,"op":10812,"st":0,"bm":0},{"ddd":0,"ind":4,"ty":4,"nm":"Board","parent":2,"tt":2,"sr":1,"ks":{"o":{"a":1,"k":[{"i":{"x":[0.833],"y":[0.833]},"o":{"x":[0.167],"y":[0.167]},"t":84,"s":[0]},{"t":98,"s":[100]}],"ix":11},"r":{"a":0,"k":-4.6,"ix":10},"p":{"a":0,"k":[139.149,84.001,0],"ix":2},"a":{"a":0,"k":[-5.981,-44.258,0],"ix":1},"s":{"a":0,"k":[137.161,165.428,100],"ix":6}},"ao":0,"shapes":[{"ty":"gr","it":[{"ty":"rc","d":1,"s":{"a":0,"k":[197.368,93.301],"ix":2},"p":{"a":0,"k":[0,0],"ix":3},"r":{"a":0,"k":10,"ix":4},"nm":"Rectangle Path 1","mn":"ADBE Vector Shape - Rect","hd":false},{"ty":"st","c":{"a":0,"k":[0.101960791794,0.180392156863,0.207843152214,1],"ix":3},"o":{"a":0,"k":100,"ix":4},"w":{"a":0,"k":0,"ix":5},"lc":1,"lj":1,"ml":4,"bm":0,"nm":"Stroke 1","mn":"ADBE Vector Graphic - Stroke","hd":false},{"ty":"gf","o":{"a":0,"k":100,"ix":10},"r":1,"bm":0,"g":{"p":3,"k":{"a":0,"k":[0,1,0.961,0,0.5,1,0.859,0,1,1,0.758,0],"ix":9}},"s":{"a":0,"k":[0,0],"ix":5},"e":{"a":0,"k":[100,0],"ix":6},"t":1,"nm":"Gradient Fill 1","mn":"ADBE Vector Graphic - G-Fill","hd":false},{"ty":"tr","p":{"a":0,"k":[-5.981,-44.258],"ix":2},"a":{"a":0,"k":[0,0],"ix":1},"s":{"a":0,"k":[100,100],"ix":3},"r":{"a":0,"k":0,"ix":6},"o":{"a":0,"k":100,"ix":7},"sk":{"a":0,"k":0,"ix":4},"sa":{"a":0,"k":0,"ix":5},"nm":"Transform"}],"nm":"Rectangle 1","np":3,"cix":2,"bm":0,"ix":1,"mn":"ADBE Vector Group","hd":false}],"ip":0,"op":10812,"st":0,"bm":0},{"ddd":0,"ind":5,"ty":4,"nm":"ALpha","td":1,"sr":1,"ks":{"o":{"a":0,"k":100,"ix":11},"r":{"a":0,"k":0,"ix":10},"p":{"a":0,"k":[378,250,0],"ix":2},"a":{"a":0,"k":[0,0,0],"ix":1},"s":{"a":0,"k":[100,111.715,100],"ix":6}},"ao":0,"shapes":[{"ty":"gr","it":[{"ty":"rc","d":1,"s":{"a":0,"k":[234,106],"ix":2},"p":{"a":0,"k":[0,0],"ix":3},"r":{"a":0,"k":0,"ix":4},"nm":"Rectangle Path 1","mn":"ADBE Vector Shape - Rect","hd":false},{"ty":"st","c":{"a":0,"k":[0.527842981675,0.117987995522,0.276641995299,1],"ix":3},"o":{"a":0,"k":100,"ix":4},"w":{"a":0,"k":0,"ix":5},"lc":1,"lj":1,"ml":4,"bm":0,"nm":"Stroke 1","mn":"ADBE Vector Graphic - Stroke","hd":false},{"ty":"fl","c":{"a":0,"k":[0.117646998985,0.60784295774,0.050980003207,1],"ix":4},"o":{"a":0,"k":100,"ix":5},"r":1,"bm":0,"nm":"Fill 1","mn":"ADBE Vector Graphic - Fill","hd":false},{"ty":"tr","p":{"a":0,"k":[15,186],"ix":2},"a":{"a":0,"k":[0,0],"ix":1},"s":{"a":0,"k":[126.446,100],"ix":3},"r":{"a":0,"k":0,"ix":6},"o":{"a":0,"k":100,"ix":7},"sk":{"a":0,"k":0,"ix":4},"sa":{"a":0,"k":0,"ix":5},"nm":"Transform"}],"nm":"Rectangle 1","np":3,"cix":2,"bm":0,"ix":1,"mn":"ADBE Vector Group","hd":false}],"ip":0,"op":10812,"st":0,"bm":0},{"ddd":0,"ind":6,"ty":4,"nm":"Hand Outlines","tt":2,"sr":1,"ks":{"o":{"a":1,"k":[{"i":{"x":[0.833],"y":[0.833]},"o":{"x":[0.167],"y":[0.167]},"t":84,"s":[0]},{"t":98,"s":[100]}],"ix":11},"r":{"a":0,"k":0,"ix":10},"p":{"a":1,"k":[{"i":{"x":0.16,"y":1},"o":{"x":0.84,"y":0},"t":32.365,"s":[379.355,579.164,0],"to":[0,-40.417,0],"ti":[0,40.417,0]},{"t":144,"s":[379.355,336.664,0]}],"ix":2},"a":{"a":0,"k":[26.196,60.257,0],"ix":1},"s":{"a":0,"k":[100,100,100],"ix":6}},"ao":0,"shapes":[{"ty":"gr","it":[{"ind":0,"ty":"sh","ix":1,"ks":{"a":0,"k":{"i":[[3.41,3.396],[4.845,1.102],[7.397,1.39],[1.458,0.152],[7.533,-2.206],[4.818,-2.273],[3.182,-2.091],[9.777,2.889],[-6.174,-0.428],[-1.801,3.717],[0.845,0.764]],"o":[[3.312,-1.645],[2.881,-1.581],[-1.439,-0.271],[8.339,2.358],[6.091,1.454],[3.182,1.727],[4.617,5.442],[0.248,1.894],[8.453,0.586],[0.951,-1.961],[1.487,-1.016]],"v":[[10.285,1.417],[9.197,-10.719],[6.539,-21.368],[2.207,-22.006],[4.272,-10.525],[6.819,1.474],[7.363,11.746],[-14.042,16.524],[-6.12,21.42],[10.618,16.314],[10.034,11.711]],"c":true},"ix":2},"nm":"Path 1","mn":"ADBE Vector Shape - Group","hd":false},{"ty":"mm","mm":4,"nm":"Merge Paths 1","mn":"ADBE Vector Filter - Merge","hd":false},{"ty":"fl","c":{"a":0,"k":[0.948999980852,0.702000038297,0.430999995213,1],"ix":4},"o":{"a":0,"k":100,"ix":5},"r":1,"bm":0,"nm":"Fill 1","mn":"ADBE Vector Graphic - Fill","hd":false},{"ty":"tr","p":{"a":0,"k":[19.362,52.791],"ix":2},"a":{"a":0,"k":[0,0],"ix":1},"s":{"a":0,"k":[100,100],"ix":3},"r":{"a":0,"k":0,"ix":6},"o":{"a":0,"k":100,"ix":7},"sk":{"a":0,"k":0,"ix":4},"sa":{"a":0,"k":0,"ix":5},"nm":"Transform"}],"nm":"Group 5","np":3,"cix":2,"bm":0,"ix":5,"mn":"ADBE Vector Group","hd":false},{"ty":"gr","it":[{"ind":0,"ty":"sh","ix":1,"ks":{"a":0,"k":{"i":[[7.149,-1.056],[0.43,-2.05],[0.753,-2.26],[-1.172,-1.924],[0.526,-1.578],[-1.498,-1.847],[0.445,-2.076],[-8.454,-0.586],[-1.802,3.716],[0.845,0.764],[3.411,3.397],[4.845,1.102],[7.397,1.391]],"o":[[-3.742,0.552],[-0.94,4.487],[-0.754,2.26],[1.172,1.926],[-0.742,2.223],[1.098,1.353],[-0.294,1.372],[8.453,0.586],[0.95,-1.962],[1.487,-1.016],[3.311,-1.644],[2.881,-1.581],[-5.68,-1.068]],"v":[[-9.393,-21.264],[-15.637,-17.018],[-14.297,-7.727],[-14.046,-0.111],[-13.422,5.079],[-12.122,10.435],[-11.446,15.161],[-3.584,21.734],[13.155,16.628],[12.569,12.025],[12.82,1.73],[11.732,-10.406],[9.074,-21.054]],"c":true},"ix":2},"nm":"Path 1","mn":"ADBE Vector Shape - Group","hd":false},{"ty":"mm","mm":4,"nm":"Merge Paths 1","mn":"ADBE Vector Filter - Merge","hd":false},{"ty":"fl","c":{"a":0,"k":[0.991999966491,0.816000007181,0.528999956916,1],"ix":4},"o":{"a":0,"k":100,"ix":5},"r":1,"bm":0,"nm":"Fill 1","mn":"ADBE Vector Graphic - Fill","hd":false},{"ty":"tr","p":{"a":0,"k":[16.827,52.476],"ix":2},"a":{"a":0,"k":[0,0],"ix":1},"s":{"a":0,"k":[100,100],"ix":3},"r":{"a":0,"k":0,"ix":6},"o":{"a":0,"k":100,"ix":7},"sk":{"a":0,"k":0,"ix":4},"sa":{"a":0,"k":0,"ix":5},"nm":"Transform"}],"nm":"Group 6","np":3,"cix":2,"bm":0,"ix":6,"mn":"ADBE Vector Group","hd":false},{"ty":"gr","it":[{"ind":0,"ty":"sh","ix":1,"ks":{"a":0,"k":{"i":[[0,-2.287],[0,0],[0,2.995],[0,0]],"o":[[0,0],[0,2.995],[0,0],[0,-1.834]],"v":[[-5.424,-24.684],[-5.424,23.976],[5.424,23.976],[5.424,-24.684]],"c":true},"ix":2},"nm":"Path 1","mn":"ADBE Vector Shape - Group","hd":false},{"ty":"mm","mm":4,"nm":"Merge Paths 1","mn":"ADBE Vector Filter - Merge","hd":false},{"ty":"fl","c":{"a":0,"k":[0.404000016755,0.136999990426,0,1],"ix":4},"o":{"a":0,"k":100,"ix":5},"r":1,"bm":0,"nm":"Fill 1","mn":"ADBE Vector Graphic - Fill","hd":false},{"ty":"tr","p":{"a":0,"k":[14.522,52.646],"ix":2},"a":{"a":0,"k":[0,0],"ix":1},"s":{"a":0,"k":[100,100],"ix":3},"r":{"a":0,"k":0,"ix":6},"o":{"a":0,"k":100,"ix":7},"sk":{"a":0,"k":0,"ix":4},"sa":{"a":0,"k":0,"ix":5},"nm":"Transform"}],"nm":"Group 12","np":3,"cix":2,"bm":0,"ix":12,"mn":"ADBE Vector Group","hd":false},{"ty":"gr","it":[{"ind":0,"ty":"sh","ix":1,"ks":{"a":0,"k":{"i":[[0,0],[0,0],[-2.995,0],[0,2.996],[0,0]],"o":[[0,0],[0,2.996],[2.996,0],[0,0],[0,0]],"v":[[-5.424,-46.979],[-5.424,41.554],[0,46.979],[5.424,41.554],[5.424,-46.979]],"c":true},"ix":2},"nm":"Path 1","mn":"ADBE Vector Shape - Group","hd":false},{"ty":"mm","mm":4,"nm":"Merge Paths 1","mn":"ADBE Vector Filter - Merge","hd":false},{"ty":"fl","c":{"a":0,"k":[0.745000023935,0.423999980852,0,1],"ix":4},"o":{"a":0,"k":100,"ix":5},"r":1,"bm":0,"nm":"Fill 1","mn":"ADBE Vector Graphic - Fill","hd":false},{"ty":"tr","p":{"a":0,"k":[14.522,47.229],"ix":2},"a":{"a":0,"k":[0,0],"ix":1},"s":{"a":0,"k":[100,100],"ix":3},"r":{"a":0,"k":0,"ix":6},"o":{"a":0,"k":100,"ix":7},"sk":{"a":0,"k":0,"ix":4},"sa":{"a":0,"k":0,"ix":5},"nm":"Transform"}],"nm":"Group 13","np":3,"cix":2,"bm":0,"ix":13,"mn":"ADBE Vector Group","hd":false}],"ip":0,"op":10812,"st":0,"bm":0},{"ddd":0,"ind":7,"ty":4,"nm":"ALpha 3","td":1,"sr":1,"ks":{"o":{"a":0,"k":100,"ix":11},"r":{"a":0,"k":0,"ix":10},"p":{"a":0,"k":[378,250,0],"ix":2},"a":{"a":0,"k":[0,0,0],"ix":1},"s":{"a":0,"k":[100,111.715,100],"ix":6}},"ao":0,"shapes":[{"ty":"gr","it":[{"ty":"rc","d":1,"s":{"a":0,"k":[234,106],"ix":2},"p":{"a":0,"k":[0,0],"ix":3},"r":{"a":0,"k":0,"ix":4},"nm":"Rectangle Path 1","mn":"ADBE Vector Shape - Rect","hd":false},{"ty":"st","c":{"a":0,"k":[0.527842981675,0.117987995522,0.276641995299,1],"ix":3},"o":{"a":0,"k":100,"ix":4},"w":{"a":0,"k":0,"ix":5},"lc":1,"lj":1,"ml":4,"bm":0,"nm":"Stroke 1","mn":"ADBE Vector Graphic - Stroke","hd":false},{"ty":"fl","c":{"a":0,"k":[0.117646998985,0.60784295774,0.050980003207,1],"ix":4},"o":{"a":0,"k":100,"ix":5},"r":1,"bm":0,"nm":"Fill 1","mn":"ADBE Vector Graphic - Fill","hd":false},{"ty":"tr","p":{"a":0,"k":[15,186],"ix":2},"a":{"a":0,"k":[0,0],"ix":1},"s":{"a":0,"k":[126.446,100],"ix":3},"r":{"a":0,"k":0,"ix":6},"o":{"a":0,"k":100,"ix":7},"sk":{"a":0,"k":0,"ix":4},"sa":{"a":0,"k":0,"ix":5},"nm":"Transform"}],"nm":"Rectangle 1","np":3,"cix":2,"bm":0,"ix":1,"mn":"ADBE Vector Group","hd":false}],"ip":0,"op":10812,"st":0,"bm":0},{"ddd":0,"ind":8,"ty":1,"nm":"Arm","parent":6,"tt":2,"sr":1,"ks":{"o":{"a":1,"k":[{"i":{"x":[0.833],"y":[0.833]},"o":{"x":[0.167],"y":[0.167]},"t":84,"s":[0]},{"t":98,"s":[100]}],"ix":11},"r":{"a":0,"k":0,"ix":10},"p":{"a":0,"k":[32.34,71.27,0],"ix":2},"a":{"a":0,"k":[375,250,0],"ix":1},"s":{"a":0,"k":[100,100,100],"ix":6}},"ao":0,"hasMask":true,"masksProperties":[{"inv":false,"mode":"f","pt":{"a":0,"k":{"i":[[-0.032,1.777],[-3.304,-1.023],[-1.809,-5.427],[-1.088,-7.543],[-2.281,-13.923],[-5.585,-11.878],[8.919,0.22],[0.328,16.483],[0.348,6.893]],"o":[[0.076,-4.171],[3.304,1.023],[1.809,5.428],[1.328,9.208],[2.281,13.923],[-4.117,0.037],[-1.809,-15.496],[-0.334,-16.778],[-0.285,-5.637]],"v":[[360.963,207.916],[367.885,197.218],[370.796,210.118],[377.796,225.457],[379.554,257.605],[393.179,303.649],[360.79,303.584],[357.155,251.525],[361.102,217.863]],"c":true},"ix":1},"o":{"a":0,"k":100,"ix":3},"x":{"a":0,"k":0,"ix":4},"nm":"Mask 1"}],"sw":750,"sh":500,"sc":"#fdd087","ip":0,"op":10812,"st":0,"bm":0},{"ddd":0,"ind":9,"ty":4,"nm":"Hole02","sr":1,"ks":{"o":{"a":0,"k":100,"ix":11},"r":{"a":0,"k":0,"ix":10},"p":{"a":0,"k":[391,377,0],"ix":2},"a":{"a":0,"k":[12,183,0],"ix":1},"s":{"a":1,"k":[{"i":{"x":[0.16,0.16,0.16],"y":[1,1,1]},"o":{"x":[0.84,0.84,0.84],"y":[0,0,0]},"t":0,"s":[0,100,100]},{"t":65,"s":[100,100,100]}],"ix":6}},"ao":0,"shapes":[{"ty":"gr","it":[{"d":1,"ty":"el","s":{"a":0,"k":[246,42],"ix":2},"p":{"a":0,"k":[0,0],"ix":3},"nm":"Ellipse Path 1","mn":"ADBE Vector Shape - Ellipse","hd":false},{"ty":"st","c":{"a":0,"k":[0.101960791794,0.180392156863,0.207843152214,1],"ix":3},"o":{"a":0,"k":100,"ix":4},"w":{"a":0,"k":0,"ix":5},"lc":1,"lj":1,"ml":4,"bm":0,"nm":"Stroke 1","mn":"ADBE Vector Graphic - Stroke","hd":false},{"ty":"fl","c":{"a":0,"k":[0.294117647059,0.027450982262,0.133333333333,1],"ix":4},"o":{"a":0,"k":100,"ix":5},"r":1,"bm":0,"nm":"Fill 1","mn":"ADBE Vector Graphic - Fill","hd":false},{"ty":"tr","p":{"a":0,"k":[12,183],"ix":2},"a":{"a":0,"k":[0,0],"ix":1},"s":{"a":0,"k":[100,100],"ix":3},"r":{"a":0,"k":0,"ix":6},"o":{"a":0,"k":100,"ix":7},"sk":{"a":0,"k":0,"ix":4},"sa":{"a":0,"k":0,"ix":5},"nm":"Transform"}],"nm":"Ellipse 1","np":3,"cix":2,"bm":0,"ix":1,"mn":"ADBE Vector Group","hd":false}],"ip":0,"op":10812,"st":0,"bm":0}],"markers":[]}